{
  "gitSyncId": "63636afbe0820924e1708dd5_63636afce0820924e1708e66",
  "id": "Satish Last 100 PR perf_fetchRunsOfMeta",
  "pluginId": "postgres-plugin",
  "pluginType": "DB",
  "unpublishedAction": {
    "actionConfiguration": {
      "body": "SELECT * FROM public.run where meta={{this.params.meta}} and metric in ({{PR_Run_meta.getMetricsToShow()}});\n\n",
      "encodeParamsToggle": true,
      "paginationType": "NONE",
      "pluginSpecifiedTemplates": [
        {
          "value": true
        }
      ],
      "timeoutInMillisecond": 10000
    },
    "confirmBeforeExecute": false,
    "datasource": {
      "id": "performance-supabase-satish",
      "isAutoGenerated": false,
      "name": "performance-supabase-satish",
      "pluginId": "postgres-plugin"
    },
    "dynamicBindingPathList": [
      {
        "key": "body"
      }
    ],
    "executeOnLoad": false,
    "name": "fetchRunsOfMeta",
    "pageId": "Satish Last 100 PR perf",
    "userSetOnLoad": true
  }
}